README.md
harmonic/__init__.py
harmonic/assets/images/adi-logo.png
harmonic/assets/images/favicon.svg
harmonic/assets/stylesheets/harmonic-mkdocs.css
harmonic/assets/stylesheets/harmonic.css
harmonic/main.html
harmonic/mkdocs_theme.yml
harmonic/partials/copyright.html
harmonic/partials/footer.html
harmonic/partials/social.html
adi_mkdocs_harmonic-0.7.0.dist-info/METADATA
adi_mkdocs_harmonic-0.7.0.dist-info/WHEEL
adi_mkdocs_harmonic-0.7.0.dist-info/entry_points.txt
adi_mkdocs_harmonic-0.7.0.dist-info/RECORD
