Metadata-Version: 2.1
Name: adi-mkdocs-harmonic
Version: 0.7.0
Summary: An ADI Harmonic theme for mkdocs based on mkdocs-material
Home-page: https://github.com/analogdevicesinc/harmonic-mkdocs-theme
License: Apache-2.0
Keywords: mkdocs,mkdocs-material,harmonic
Requires-Python: >=3.10,<4.0
Classifier: License :: OSI Approved :: Apache Software License
Classifier: Programming Language :: Python :: 3
Classifier: Programming Language :: Python :: 3.10
Classifier: Programming Language :: Python :: 3.11
Classifier: Programming Language :: Python :: 3.12
Requires-Dist: mkdocs (>=1.5.3,<2.0.0)
Requires-Dist: mkdocs-material (>=9.5.11,<10.0.0)
Project-URL: Issue Tracker, https://github.com/analogdevicesinc/harmonic-mkdocs-theme/issues
Project-URL: Repository, https://github.com/analogdevicesinc/harmonic-mkdocs-theme
